gpt_db_core-0.1.1.dist-info/licenses/LICENSE
main/__init__.py
main/admin.py
main/apps.py
main/cli.py
main/db_bridge.py
main/models.py
main/nn_mini.py
main/tests.py
main/tokenizer.py
main/views.py
main/management/commands/chat.py
main/management/commands/init_run.py
main/management/commands/train.py
main/migrations/0001_initial.py
main/migrations/0002_chatsession_predictionlog_session.py
main/migrations/__init__.py
gpt_db_core-0.1.1.dist-info/METADATA
gpt_db_core-0.1.1.dist-info/WHEEL
gpt_db_core-0.1.1.dist-info/entry_points.txt
gpt_db_core-0.1.1.dist-info/top_level.txt
gpt_db_core-0.1.1.dist-info/RECORD
