Metadata-Version: 2.4
Name: gpt_db-core
Version: 0.1.1
Summary: A Django + PyTorch neural database that learns, trains, and chats directly from your database.
Author-email: Gerson De La Cruz <qaputancana@gmail.com>
License: GPT-DB License  
Project-URL: Homepage, https://github.com/gersondelacruz/gptdb
Project-URL: Documentation, https://pypi.org/project/gptdb-core/
Project-URL: Issues, https://github.com/gersondelacruz/gptdb/issues
Keywords: gpt,django,pytorch,ai,database,neural,nlp,transformer
Classifier: Development Status :: 4 - Beta
Classifier: Intended Audience :: Developers
Classifier: License :: Other/Proprietary License
Classifier: Programming Language :: Python :: 3
Classifier: Programming Language :: Python :: 3.9
Classifier: Topic :: Scientific/Engineering :: Artificial Intelligence
Classifier: Framework :: Django
Classifier: Operating System :: OS Independent
Requires-Python: >=3.9
License-File: LICENSE
Requires-Dist: django>=4.0
Requires-Dist: torch>=2.0.0
Requires-Dist: numpy>=1.22.0
Dynamic: license-file
